Metadata-Version: 2.1
Name: pytest-freeze-reqs
Version: 0.1.8
Summary: Check if requirement files are frozen
Home-page: https://github.com/drozdowsky/pytest-freeze-reqs/
Author: drozdowsky
Author-email: hdrozdow+github@pm.me
License: MIT
Platform: UNKNOWN
Classifier: Framework :: Pytest
